CakeApi/CakeApiUtilities.py
CakeApi/__init__.py
CakeApi-1.0.5.dist-info/LICENSE.txt
CakeApi-1.0.5.dist-info/METADATA
CakeApi-1.0.5.dist-info/WHEEL
CakeApi-1.0.5.dist-info/top_level.txt
CakeApi-1.0.5.dist-info/RECORD
