Metadata-Version: 2.1
Name: CakeApi
Version: 1.0.5
Summary: Using this module you can create a API collection and it also has lots of utilities to validate the response, status code, store a value in collection variable etc.
Home-page: https://www.linkedin.com/in/krishna-kumar-859a73134
Author: Krishna Kumar Viswanathan
Author-email: krishnaForTestAutomation@gmail.com
License: MIT
Keywords: API,Rest API,API Collection,Test Automation,API test automation framework,Automation framework
Platform: UNKNOWN
Classifier: Programming Language :: Python :: 3
Classifier: License :: OSI Approved :: MIT License
Classifier: Operating System :: OS Independent
